django_pev/__init__.py
django_pev/admin.py
django_pev/apps.py
django_pev/dalibo.py
django_pev/exceptions.py
django_pev/models.py
django_pev/tests.py
django_pev/urls.py
django_pev/views.py
django_pev/migrations/0001_enable_extensions.py
django_pev/migrations/0002_update_extension.py
django_pev/migrations/__init__.py
django_pev/templates/django_pev/base.html
django_pev/templates/django_pev/connections.html
django_pev/templates/django_pev/explain.html
django_pev/templates/django_pev/index.html
django_pev/templates/django_pev/indexes_view.html
django_pev/templates/django_pev/live_queries.html
django_pev/templates/django_pev/maintenance.html
django_pev/templates/django_pev/pev_embedded.html
django_pev/templates/django_pev/queries.html
django_pev/templates/django_pev/space.html
django_pev/utils/__init__.py
django_pev/utils/index_lookup.sql
django_pev/utils/indexes.py
django_pev/utils/live_connections.py
django_pev/utils/maintenance.py
django_pev/utils/queries.py
django_pev/utils/space.py
django_pev-1.0.2.dist-info/METADATA
django_pev-1.0.2.dist-info/WHEEL
django_pev-1.0.2.dist-info/licenses/LICENSE
django_pev-1.0.2.dist-info/RECORD
