Metadata-Version: 2.4
Name: django-pev
Version: 1.0.2
Summary: Context manager to upload explain plans to https://explain.dalibo.com/
Author-email: william chu <william.chu@uptickhq.com>
License-File: LICENSE
Requires-Python: >=3.10
Requires-Dist: django<5.2.0,>=3.2
Requires-Dist: psycopg2~=2.9.0
Requires-Dist: sqlglot>=18.13.0
